specklegen/__init__.py
specklegen/synthetic_data_generator.py
specklegen-0.1.7.dist-info/LICENSE.txt
specklegen-0.1.7.dist-info/METADATA
specklegen-0.1.7.dist-info/WHEEL
specklegen-0.1.7.dist-info/top_level.txt
specklegen-0.1.7.dist-info/RECORD
