Metadata-Version: 2.1
Name: specklegen
Version: 0.1.7
Summary: Generate sequences of random speckle patterns and defining optical flow fields.
Home-page: https://github.com/Computational-Ocularscience/KinemaNet
Author: Fisseha A. Ferede
Author-email: fissehaad[at]gmail.com
Classifier: Programming Language :: Python :: 3
Classifier: License :: OSI Approved :: MIT License
Classifier: Operating System :: OS Independent
Requires-Python: >=3.6
License-File: LICENSE.txt
